odoo8_addon_shopinvader_google_shopping-8.0.1.0.0.99.dev5-py3.8-nspkg.pth
odoo_addons/shopinvader_google_shopping/__init__.py
odoo_addons/shopinvader_google_shopping/__openerp__.py
odoo_addons/shopinvader_google_shopping/data/ir_cron.xml
odoo_addons/shopinvader_google_shopping/data/ir_parameter.xml
odoo_addons/shopinvader_google_shopping/models/__init__.py
odoo_addons/shopinvader_google_shopping/models/backend.py
odoo_addons/shopinvader_google_shopping/models/google_category.py
odoo_addons/shopinvader_google_shopping/models/product.py
odoo_addons/shopinvader_google_shopping/security/ir.model.access.csv
odoo_addons/shopinvader_google_shopping/views/google_category_view.xml
odoo_addons/shopinvader_google_shopping/views/product_view.xml
odoo_addons/shopinvader_google_shopping/wizard/__init__.py
odoo_addons/shopinvader_google_shopping/wizard/import_google_category.py
odoo_addons/shopinvader_google_shopping/wizard/import_google_category_view.xml
odoo8_addon_shopinvader_google_shopping-8.0.1.0.0.99.dev5.dist-info/METADATA
odoo8_addon_shopinvader_google_shopping-8.0.1.0.0.99.dev5.dist-info/WHEEL
odoo8_addon_shopinvader_google_shopping-8.0.1.0.0.99.dev5.dist-info/namespace_packages.txt
odoo8_addon_shopinvader_google_shopping-8.0.1.0.0.99.dev5.dist-info/top_level.txt
odoo8_addon_shopinvader_google_shopping-8.0.1.0.0.99.dev5.dist-info/RECORD
