Metadata-Version: 2.1
Name: odoo8-addon-shopinvader-google-shopping
Version: 8.0.1.0.0.99.dev5
Summary: Export your product in google shopping
Home-page: https://www.akretion.com
Author: Akretion
License: AGPL-3
Platform: UNKNOWN
Classifier: Programming Language :: Python
Classifier: Framework :: Odoo
Classifier: Framework :: Odoo :: 8.0
Classifier: License :: OSI Approved :: GNU Affero General Public License v3
Requires-Python: ~=2.7
Requires-Dist: odoo8-addon-shopinvader
Requires-Dist: odoo (<9.0a,>=8.0a)
